maestrowf/__init__.py
maestrowf/abstracts/__init__.py
maestrowf/abstracts/abstractclassmethod.py
maestrowf/abstracts/containers/__init__.py
maestrowf/abstracts/enums/__init__.py
maestrowf/abstracts/envobject.py
maestrowf/abstracts/graph.py
maestrowf/abstracts/interfaces/__init__.py
maestrowf/abstracts/interfaces/flux.py
maestrowf/abstracts/interfaces/schedulerscriptadapter.py
maestrowf/abstracts/interfaces/scriptadapter.py
maestrowf/abstracts/specification.py
maestrowf/conductor.py
maestrowf/datastructures/__init__.py
maestrowf/datastructures/core/__init__.py
maestrowf/datastructures/core/executiongraph.py
maestrowf/datastructures/core/parameters.py
maestrowf/datastructures/core/study.py
maestrowf/datastructures/core/studyenvironment.py
maestrowf/datastructures/dag.py
maestrowf/datastructures/environment/__init__.py
maestrowf/datastructures/environment/gitdependency.py
maestrowf/datastructures/environment/pathdependency.py
maestrowf/datastructures/environment/script.py
maestrowf/datastructures/environment/variable.py
maestrowf/interfaces/__init__.py
maestrowf/interfaces/script/__init__.py
maestrowf/interfaces/script/_flux/__init__.py
maestrowf/interfaces/script/_flux/flux0_17_0.py
maestrowf/interfaces/script/_flux/flux0_18_0.py
maestrowf/interfaces/script/_flux/flux0_26_0.py
maestrowf/interfaces/script/_flux/flux0_49_0.py
maestrowf/interfaces/script/fluxscriptadapter.py
maestrowf/interfaces/script/localscriptadapter.py
maestrowf/interfaces/script/lsfscriptadapter.py
maestrowf/interfaces/script/slurmscriptadapter.py
maestrowf/maestro.py
maestrowf/specification/__init__.py
maestrowf/specification/schemas/yamlspecification.json
maestrowf/specification/yamlspecification.py
maestrowf/utils.py
maestrowf-1.1.11.dist-info/LICENSE
maestrowf-1.1.11.dist-info/METADATA
maestrowf-1.1.11.dist-info/WHEEL
maestrowf-1.1.11.dist-info/entry_points.txt
maestrowf-1.1.11.dist-info/RECORD
