Metadata-Version: 2.1
Name: maestrowf
Version: 1.1.11
Summary: A tool to easily orchestrate general computational workflows both locally and on supercomputers.
Home-page: https://github.com/llnl/maestrowf
License: MIT
Author: Francesco Di Natale
Author-email: dinatale3@llnl.gov
Maintainer: Francesco Di Natale
Maintainer-email: dinatale3@llnl.gov
Requires-Python: >=3.8,<4.0
Classifier: Development Status :: 5 - Production/Stable
Classifier: Intended Audience :: Developers
Classifier: Intended Audience :: Education
Classifier: Intended Audience :: Science/Research
Classifier: License :: OSI Approved :: MIT License
Classifier: Operating System :: MacOS :: MacOS X
Classifier: Operating System :: Unix
Classifier: Programming Language :: Python :: 3
Classifier: Programming Language :: Python :: 3.8
Classifier: Programming Language :: Python :: 3.9
Classifier: Programming Language :: Python :: 3.10
Classifier: Programming Language :: Python :: 3.11
Classifier: Programming Language :: Python :: 3.12
Classifier: Programming Language :: Python :: 3.13
Classifier: Topic :: Scientific/Engineering
Classifier: Topic :: System :: Distributed Computing
Requires-Dist: coloredlogs
Requires-Dist: dill
Requires-Dist: filelock
Requires-Dist: jsonschema (>=3.2.0)
Requires-Dist: packaging (>=22.0)
Requires-Dist: pyyaml (>=4.2b1)
Requires-Dist: rich
Requires-Dist: six
Requires-Dist: tabulate
Project-URL: Bug Tracker, https://github.com/LLNL/maestrowf/issues
Project-URL: Documentation, https://maestrowf.readthedocs.io/
Project-URL: Discussions, https://github.com/LLNL/maestrowf/discussions
